wrapchain/__init__.py
wrapchain/main.py
wrapchain/wrapchain.py
wrapchain-0.0.5.dist-info/METADATA
wrapchain-0.0.5.dist-info/WHEEL
wrapchain-0.0.5.dist-info/RECORD
