Metadata-Version: 2.1
Name: wrapchain
Version: 0.0.5
Summary: 
Author: kyaukyuai
Author-email: y.kakui@gmail.com
Requires-Python: >=3.10.0,<3.11
Classifier: Programming Language :: Python :: 3
Classifier: Programming Language :: Python :: 3.10
Requires-Dist: langchain (>=0.1.16,<0.2.0)
Requires-Dist: langchain-anthropic (>=0.1.8,<0.2.0)
Requires-Dist: pillow (>=10.3.0,<11.0.0)
Requires-Dist: python-dotenv (>=1.0.1,<2.0.0)
